pyemailmonitor/__init__.py
pyemailmonitor/cli.py
pyemailmonitor/exceptions.py
pyemailmonitor/monitor.py
pyemailmonitor/templates.py
pyemailmonitor-1.2.0.dist-info/licenses/LICENSE
pyemailmonitor-1.2.0.dist-info/METADATA
pyemailmonitor-1.2.0.dist-info/WHEEL
pyemailmonitor-1.2.0.dist-info/entry_points.txt
pyemailmonitor-1.2.0.dist-info/top_level.txt
pyemailmonitor-1.2.0.dist-info/RECORD
