Metadata-Version: 2.4
Name: pyemailmonitor
Version: 1.2.0
Summary: Python email monitoring library for program status notifications
Home-page: https://github.com/PoseZhaoyutao/pyemailmonitor
Author: Zhao Yutao
Author-email: zhaoyutao22@mails.ucas.ac.cn
Classifier: Programming Language :: Python :: 3
Classifier: License :: OSI Approved :: MIT License
Classifier: Operating System :: OS Independent
Requires-Python: >=3.6
License-File: LICENSE
Dynamic: author
Dynamic: author-email
Dynamic: classifier
Dynamic: description
Dynamic: description-content-type
Dynamic: home-page
Dynamic: license-file
Dynamic: requires-python
Dynamic: summary
